tap_checkly/__init__.py
tap_checkly/__main__.py
tap_checkly/client.py
tap_checkly/openapi.json
tap_checkly/streams.py
tap_checkly/tap.py
tap_checkly-0.5.5.dist-info/METADATA
tap_checkly-0.5.5.dist-info/WHEEL
tap_checkly-0.5.5.dist-info/entry_points.txt
tap_checkly-0.5.5.dist-info/licenses/LICENSE
tap_checkly-0.5.5.dist-info/RECORD
