Metadata-Version: 2.4
Name: tap-checkly
Version: 0.5.5
Summary: Singer tap for Checkly, built with the Meltano SDK for Singer Taps.
Project-URL: Documentation, https://github.com/reservoir-data/tap-checkly/#readme
Project-URL: Homepage, https://github.com/reservoir-data/tap-checkly
Project-URL: Repository, https://github.com/reservoir-data/tap-checkly
Author-email: Edgar Ramírez-Mondragón <edgarrm358@gmail.com>
Maintainer-email: Edgar Ramírez-Mondragón <edgarrm358@gmail.com>
License-Expression: Apache-2.0
License-File: LICENSE
Keywords: Checkly,ELT,singer.io
Classifier: Operating System :: OS Independent
Classifier: Programming Language :: Python :: 3 :: Only
Classifier: Programming Language :: Python :: 3.11
Classifier: Programming Language :: Python :: 3.12
Classifier: Programming Language :: Python :: 3.13
Classifier: Programming Language :: Python :: 3.14
Requires-Python: >=3.11
Requires-Dist: singer-sdk~=0.51.0
Requires-Dist: typing-extensions>=4.15; python_full_version < '3.12'
